{
  "variants": {
    "normal": {
      "model": "basicmachinery:crusher"
    },
    "burning=false,facing=north,working=false": {
      "model": "basicmachinery:crusher"
    },
    "burning=false,facing=east,working=false": {
      "model": "basicmachinery:crusher",
      "y": 90
    },
    "burning=false,facing=south,working=false": {
        "model": "basicmachinery:crusher",
        "y": 180
      },
    "burning=false,facing=west,working=false": {
      "model": "basicmachinery:crusher",
      "y": 270
    },
    "burning=false,facing=north,working=true": {
      "model": "basicmachinery:crusher_working"
    },
    "burning=false,facing=east,working=true": {
      "model": "basicmachinery:crusher_working",
      "y": 90
    },
    "burning=false,facing=south,working=true": {
      "model": "basicmachinery:crusher_working",
      "y": 180
    },
    "burning=false,facing=west,working=true": {
      "model": "basicmachinery:crusher_working",
      "y": 270
    },
    "burning=true,facing=north,working=false": {
      "model": "basicmachinery:crusher_burning"
    },
    "burning=true,facing=east,working=false": {
      "model": "basicmachinery:crusher_burning",
      "y": 90
    },
    "burning=true,facing=south,working=false": {
      "model": "basicmachinery:crusher_burning",
      "y": 180
    },
    "burning=true,facing=west,working=false": {
      "model": "basicmachinery:crusher_burning",
      "y": 270
    },
    "burning=true,facing=north,working=true": {
      "model": "basicmachinery:crusher_burning_working"
    },
    "burning=true,facing=east,working=true": {
      "model": "basicmachinery:crusher_burning_working",
      "y": 90
    },
    "burning=true,facing=south,working=true": {
      "model": "basicmachinery:crusher_burning_working",
      "y": 180
    },
    "burning=true,facing=west,working=true": {
      "model": "basicmachinery:crusher_burning_working",
      "y": 270
    }
  }
}